{
  "name": "ESPHome Firmware for Satellite1-Core-Board",
  "version": "v0.1.2.1+ld2410",
  "new_install_prompt_erase": true,
  "builds": [
    {
      "chipFamily": "ESP32-S3",
      "ota": {
        "path": "assets/firmware/esphome/production/satellite1.ld2410.ota.bin",
        "md5": "ba98db70d0b7016f37c8db1d77205dd7",
        "summary": "ESPHome Firmware for satellite1.ld2410",
        "release_url": "https://github.com/FutureProofHomes/Satellite1-ESPHome/releases/tag/v0.1.2.1/"
      },
      "parts": [
        {
          "path": "assets/firmware/esphome/production/satellite1.ld2410.factory.bin",
          "offset": 0
        }
      ]
    }
  ]
}