{
  "name": "ESPHome Firmware for Satellite1-Core-Board",
  "version": "v0.1.2.1+ld2450",
  "new_install_prompt_erase": true,
  "builds": [
    {
      "chipFamily": "ESP32-S3",
      "ota": {
        "path": "assets/firmware/esphome/production/satellite1.ld2450.ota.bin",
        "md5": "fa8eb37d80dc838953ea9a6c62e614e8",
        "summary": "ESPHome Firmware for satellite1.ld2450",
        "release_url": "https://github.com/FutureProofHomes/Satellite1-ESPHome/releases/tag/v0.1.2.1/"
      },
      "parts": [
        {
          "path": "assets/firmware/esphome/production/satellite1.ld2450.factory.bin",
          "offset": 0
        }
      ]
    }
  ]
}